xgdl/__init__.py
xgdl/eval.py
xgdl/get_data.py
xgdl/get_model.py
xgdl/nni_finetune.py
xgdl/pipeline.py
xgdl/template.py
xgdl/test_combination.py
xgdl/trainer.py
xgdl/backbones/__init__.py
xgdl/backbones/dgcnn.py
xgdl/backbones/egnn.py
xgdl/backbones/model_utils.py
xgdl/backbones/pointtrans.py
xgdl/baselines/__init__.py
xgdl/baselines/base.py
xgdl/baselines/new_method.py
xgdl/baselines/new_shapley.py
xgdl/baselines/test_method.py
xgdl/baselines/inherent/__init__.py
xgdl/baselines/inherent/asap.py
xgdl/baselines/inherent/ciga.py
xgdl/baselines/inherent/dir.py
xgdl/baselines/inherent/lri_bern.py
xgdl/baselines/inherent/lri_gaussian.py
xgdl/baselines/inherent/vgib.py
xgdl/baselines/posthoc/__init__.py
xgdl/baselines/posthoc/gnnexplainer.py
xgdl/baselines/posthoc/gnnlrp.py
xgdl/baselines/posthoc/grad.py
xgdl/baselines/posthoc/grads.py
xgdl/baselines/posthoc/new_method.py
xgdl/baselines/posthoc/orphicx.py
xgdl/baselines/posthoc/pgexplainer.py
xgdl/baselines/posthoc/pgmexplainer.py
xgdl/baselines/posthoc/shapley.py
xgdl/baselines/posthoc/subgraphx.py
xgdl/configs/actstrack.yml
xgdl/configs/dgcnn_actstrack.yml
xgdl/configs/dgcnn_plbind.yml
xgdl/configs/dgcnn_synmol.yml
xgdl/configs/dgcnn_tau3mu.yml
xgdl/configs/egnn_actstrack.yml
xgdl/configs/egnn_plbind.yml
xgdl/configs/egnn_synmol.yml
xgdl/configs/egnn_tau3mu.yml
xgdl/configs/plbind.yml
xgdl/configs/pointtrans_actstrack.yml
xgdl/configs/pointtrans_plbind.yml
xgdl/configs/pointtrans_synmol.yml
xgdl/configs/pointtrans_tau3mu.yml
xgdl/configs/synmol.yml
xgdl/configs/tau3mu.yml
xgdl/datasets/__init__.py
xgdl/datasets/actstrack.py
xgdl/datasets/plbind.py
xgdl/datasets/synmol.py
xgdl/datasets/tau3mu.py
xgdl/exps/ensemble.py
xgdl/exps/model_trustworthy.py
xgdl/exps/test_sensitivity.py
xgdl/exps/test_uncertainty.py
xgdl/exps/vary_generalization.py
xgdl/exps/vary_reliability.py
xgdl/log/rename_files.py
xgdl/result/add-post_inherent.py
xgdl/result/statistics.py
xgdl/utils/__init__.py
xgdl/utils/draw_figs.py
xgdl-0.0.4.dist-info/LICENSE
xgdl-0.0.4.dist-info/METADATA
xgdl-0.0.4.dist-info/WHEEL
xgdl-0.0.4.dist-info/top_level.txt
xgdl-0.0.4.dist-info/RECORD
