Metadata-Version: 2.1
Name: xgdl
Version: 0.0.4
Summary: Explainability Library with Geometric Deep Learning for Scientific Tasks
Author-email: Jiajun Zhu <zhuconv@gmail.com>, Siqi Miao <siqim311@gamil.com>
Project-URL: Homepage, https://github.com/Graph-COM/xgdl
Project-URL: Bug Tracker, https://github.com/Graph-COM/xgdl/issues
Classifier: Programming Language :: Python :: 3
Classifier: License :: OSI Approved :: MIT License
Classifier: Operating System :: OS Independent
Requires-Python: >=3.8
License-File: LICENSE
Requires-Dist: Bio
Requires-Dist: joblib
Requires-Dist: pandas
Requires-Dist: Pint
Requires-Dist: PyYAML
Requires-Dist: rdkit
Requires-Dist: rdkit-pypi
Requires-Dist: scikit-learn
Requires-Dist: scipy
Requires-Dist: tqdm
Requires-Dist: tensorboard
Requires-Dist: jupyter
Requires-Dist: pgmpy
Requires-Dist: torchmetrics
